graphql_adapter/__init__.py
graphql_adapter-0.0.2.dist-info/METADATA
graphql_adapter-0.0.2.dist-info/WHEEL
graphql_adapter-0.0.2.dist-info/top_level.txt
graphql_adapter-0.0.2.dist-info/RECORD
