Metadata-Version: 2.1
Name: graphql-adapter
Version: 0.0.2
Summary: GraphQL Adapter for Python.
Author: Josh XT
Author-email: josh@devxt.com
Requires-Dist: python-graphql-client
